mercuryfieldservice/__init__.py
mercuryfieldservice/base.py
mercuryfieldservice/exceptions.py
mercuryfieldservice/fields.py
mercuryfieldservice/managers.py
mercuryfieldservice/record_manager.py
mercuryfieldservice/client/__init__.py
mercuryfieldservice/client/connection.py
mercuryfieldservice/client/zendesk_manager.py
mercury_field_service-0.1.0.dist-info/LICENSE
mercury_field_service-0.1.0.dist-info/METADATA
mercury_field_service-0.1.0.dist-info/WHEEL
mercury_field_service-0.1.0.dist-info/top_level.txt
mercury_field_service-0.1.0.dist-info/RECORD
