Metadata-Version: 2.1
Name: mercury-field-service
Version: 0.1.0
Summary: ORM for Custom Objects de Zendesk
Author-email: Pedro Andrade <pedro.moisesandrade@gmail.com>
License: MIT
Project-URL: Homepage, https://github.com/BCR-CX/mercury-field-service
Project-URL: Issues, https://github.com/BCR-CX/mercury-field-service/issues
Classifier: Programming Language :: Python :: 3
Classifier: License :: OSI Approved :: MIT License
Classifier: Operating System :: OS Independent
Requires-Python: >=3.8
License-File: LICENSE
Requires-Dist: requests >=2.31.0
Requires-Dist: python-dotenv >=1.0.0
